[
  {
    "name": "Delete Locked Crates",
    "command": "entity.deleteentity codelockedhackablecrate"
  },
  {
    "name": "Delete Player Structures",
    "command": "entity.deleteby {player_name}"
  },
  {
    "name": "Destroy Target Building",
    "command": "ent destroybuilding"
  },
  {
    "name": "Delete Entity",
    "command": "entity.deleteentity {entity_name} {0|1}"
  },
  {
    "name": "Delete All Entities",
    "command": "entity.deleteentity {shortname} 0"
  },
  {
    "name": "Set Boat Corpse Duration",
    "command": "vehicle.boat_corpse_seconds {seconds}"
  },
  {
    "name": "Set Horse Decay Time",
    "command": "baseridableanimal.decayminutes {minutes}"
  },
  {
    "name": "Set Horse Dung Speed",
    "command": "baseridableanimal.dungtimescale {scale}"
  },
  {
    "name": "Set Plant Growth Speed",
    "command": "server.planttickscale {scale}"
  },
  {
    "name": "Toggle Recycler Usage",
    "command": "CanUseRecycler {0|1}"
  },
  {
    "name": "Set Recycler Speed",
    "command": "RecyclerNextRecycleTime {seconds}"
  },
  {
    "name": "Set Recycler Warmup Time",
    "command": "RecyclerStartTime {seconds}"
  },
  {
    "name": "Set Sleeping Bag Cooldown",
    "command": "bagreuseseconds {seconds}"
  },
  {
    "name": "Set Bed Cooldown",
    "command": "bedreuseseconds {seconds}"
  }
]